setup.py
sdkdemo/__init__.py
sdkdemo.egg-info/PKG-INFO
sdkdemo.egg-info/SOURCES.txt
sdkdemo.egg-info/dependency_links.txt
sdkdemo.egg-info/top_level.txt