Metadata-Version: 1.1
Name: sdkdemo
Version: 0.0.1
Summary: Demo SDK for gitlab ci auto pub
Home-page: http://github.com/comger/kpages
Author: comger@gmail.com
Author-email: comger@gmail.com
License: http://www.apache.org/licenses/LICENSE-2.0
Platform: UNKNOWN
Classifier: License :: OSI Approved :: Apache Software License
Classifier: Programming Language :: Python :: 3.7
Classifier: Programming Language :: Python :: Implementation :: CPython
Classifier: Programming Language :: Python :: Implementation :: PyPy
